PureCPP_extract/RagPUREAI_extract.cpython-311-x86_64-linux-gnu.so
PureCPP_extract/__init__.py
purecpp_extrct.libs/libgomp-25c89faf.so.1.0.0
purecpp_extrct-0.0.2.dist-info/METADATA
purecpp_extrct-0.0.2.dist-info/WHEEL
purecpp_extrct-0.0.2.dist-info/top_level.txt
purecpp_extrct-0.0.2.dist-info/RECORD
