Metadata-Version: 2.2
Name: PureCPP_extrct
Version: 0.0.2
Summary: Binding de C++ e Python
Author: Seu Nome
Author-email: seu.email@exemplo.com
Classifier: Programming Language :: Python :: 3
Classifier: Operating System :: POSIX :: Linux
Dynamic: author
Dynamic: author-email
Dynamic: classifier
Dynamic: summary
